[
  {
    "date": "2022-07-02 14:51:00",
    "price": 19269.0725
  },
  {
    "date": "2022-07-02 14:56:00",
    "price": 19269.6975
  },
  {
    "date": "2022-07-02 15:01:00",
    "price": 19261.8225
  },
  {
    "date": "2022-07-02 15:06:00",
    "price": 19261.4525
  },
  {
    "date": "2022-07-02 15:11:00",
    "price": 19270.34375
  },
  {
    "date": "2022-07-02 15:16:00",
    "price": 19245.49625
  },
  {
    "date": "2022-07-02 15:21:00",
    "price": 19232.50375
  },
  {
    "date": "2022-07-02 15:26:00",
    "price": 19184.77375
  },
  {
    "date": "2022-07-02 15:31:00",
    "price": 19169.6875
  },
  {
    "date": "2022-07-02 15:36:00",
    "price": 19187.3075
  },
  {
    "date": "2022-07-02 15:41:00",
    "price": 19191.7725
  },
  {
    "date": "2022-07-02 15:46:00",
    "price": 19182.09875
  },
  {
    "date": "2022-07-02 15:51:00",
    "price": 19202.9375
  },
  {
    "date": "2022-07-02 15:56:00",
    "price": 19214.8725
  },
  {
    "date": "2022-07-02 16:01:00",
    "price": 19211.6925
  },
  {
    "date": "2022-07-02 16:06:00",
    "price": 19211.8275
  },
  {
    "date": "2022-07-02 16:11:00",
    "price": 19221.775
  },
  {
    "date": "2022-07-02 16:16:00",
    "price": 19189.3825
  },
  {
    "date": "2022-07-02 16:21:00",
    "price": 19197.465
  },
  {
    "date": "2022-07-02 16:26:00",
    "price": 19204.37875
  },
  {
    "date": "2022-07-02 16:31:00",
    "price": 19282.3925
  },
  {
    "date": "2022-07-02 16:36:00",
    "price": 19259.2325
  },
  {
    "date": "2022-07-02 16:41:00",
    "price": 19265.05125
  },
  {
    "date": "2022-07-02 16:46:00",
    "price": 19260.77875
  },
  {
    "date": "2022-07-02 16:51:00",
    "price": 19268.995
  },
  {
    "date": "2022-07-02 16:56:00",
    "price": 19272.7175
  },
  {
    "date": "2022-07-02 17:01:00",
    "price": 19273.51875
  },
  {
    "date": "2022-07-02 17:06:00",
    "price": 19298.4975
  },
  {
    "date": "2022-07-02 17:11:00",
    "price": 19286.46375
  },
  {
    "date": "2022-07-02 17:16:00",
    "price": 19276.58125
  },
  {
    "date": "2022-07-02 17:21:00",
    "price": 19263.84125
  },
  {
    "date": "2022-07-02 17:26:00",
    "price": 19275.59875
  },
  {
    "date": "2022-07-02 17:31:00",
    "price": 19307.05375
  },
  {
    "date": "2022-07-02 17:36:00",
    "price": 19302.325
  },
  {
    "date": "2022-07-02 17:41:00",
    "price": 19294.42375
  },
  {
    "date": "2022-07-02 17:46:00",
    "price": 19274.14875
  },
  {
    "date": "2022-07-02 17:51:00",
    "price": 19265.39875
  },
  {
    "date": "2022-07-02 17:56:00",
    "price": 19281.10375
  },
  {
    "date": "2022-07-02 18:01:00",
    "price": 19276.4675
  },
  {
    "date": "2022-07-02 18:06:00",
    "price": 19256.88375
  },
  {
    "date": "2022-07-02 18:11:00",
    "price": 19272.31375
  },
  {
    "date": "2022-07-02 18:16:00",
    "price": 19269.8125
  },
  {
    "date": "2022-07-02 18:21:00",
    "price": 19252.90375
  },
  {
    "date": "2022-07-02 18:26:00",
    "price": 19246.34
  },
  {
    "date": "2022-07-02 18:31:00",
    "price": 19255.08625
  },
  {
    "date": "2022-07-02 18:36:00",
    "price": 19251.235
  },
  {
    "date": "2022-07-02 18:41:00",
    "price": 19246.41125
  },
  {
    "date": "2022-07-02 18:46:00",
    "price": 19241.45375
  },
  {
    "date": "2022-07-02 18:51:00",
    "price": 19310.32
  },
  {
    "date": "2022-07-02 18:56:00",
    "price": 19324.10875
  },
  {
    "date": "2022-07-02 19:01:00",
    "price": 19297.42125
  },
  {
    "date": "2022-07-02 19:06:00",
    "price": 19366.5625
  },
  {
    "date": "2022-07-02 19:11:00",
    "price": 19330.0475
  },
  {
    "date": "2022-07-02 19:16:00",
    "price": 19327.705
  },
  {
    "date": "2022-07-02 19:21:00",
    "price": 19337.36125
  },
  {
    "date": "2022-07-02 19:26:00",
    "price": 19283.3275
  },
  {
    "date": "2022-07-02 19:31:00",
    "price": 19227.04625
  },
  {
    "date": "2022-07-02 19:36:00",
    "price": 19184.5075
  },
  {
    "date": "2022-07-02 19:41:00",
    "price": 19213.5675
  },
  {
    "date": "2022-07-02 19:46:00",
    "price": 19209.40375
  },
  {
    "date": "2022-07-02 19:51:00",
    "price": 19226.73875
  },
  {
    "date": "2022-07-02 19:56:00",
    "price": 19245.25125
  },
  {
    "date": "2022-07-02 20:01:00",
    "price": 19248.64125
  },
  {
    "date": "2022-07-02 20:06:00",
    "price": 19220.1625
  },
  {
    "date": "2022-07-02 20:11:00",
    "price": 19232.25875
  },
  {
    "date": "2022-07-02 20:16:00",
    "price": 19235.33125
  },
  {
    "date": "2022-07-02 20:21:00",
    "price": 19207.505
  },
  {
    "date": "2022-07-02 20:26:00",
    "price": 19224.86625
  },
  {
    "date": "2022-07-02 20:31:00",
    "price": 19231.40375
  },
  {
    "date": "2022-07-02 20:36:00",
    "price": 19237.455
  },
  {
    "date": "2022-07-02 20:41:00",
    "price": 19238.43
  },
  {
    "date": "2022-07-02 20:46:00",
    "price": 19218.9675
  },
  {
    "date": "2022-07-02 20:51:00",
    "price": 19241.4625
  },
  {
    "date": "2022-07-02 20:56:00",
    "price": 19243.0175
  },
  {
    "date": "2022-07-02 21:01:00",
    "price": 19237.53125
  },
  {
    "date": "2022-07-02 21:06:00",
    "price": 19230.66125
  },
  {
    "date": "2022-07-02 21:11:00",
    "price": 19287.125
  },
  {
    "date": "2022-07-02 21:16:00",
    "price": 19296.25
  },
  {
    "date": "2022-07-02 21:21:00",
    "price": 19285.9425
  },
  {
    "date": "2022-07-02 21:26:00",
    "price": 19288.745
  },
  {
    "date": "2022-07-02 21:31:00",
    "price": 19277.0575
  },
  {
    "date": "2022-07-02 21:36:00",
    "price": 19284.83625
  },
  {
    "date": "2022-07-02 21:41:00",
    "price": 19284.51625
  },
  {
    "date": "2022-07-02 21:46:00",
    "price": 19289.6125
  },
  {
    "date": "2022-07-02 21:51:00",
    "price": 19326.545
  },
  {
    "date": "2022-07-02 21:56:00",
    "price": 19331.135
  },
  {
    "date": "2022-07-02 22:01:00",
    "price": 19327.4875
  },
  {
    "date": "2022-07-02 22:06:00",
    "price": 19326.63375
  },
  {
    "date": "2022-07-02 22:11:00",
    "price": 19312.625
  },
  {
    "date": "2022-07-02 22:16:00",
    "price": 19320.345
  },
  {
    "date": "2022-07-02 22:21:00",
    "price": 19326.4625
  },
  {
    "date": "2022-07-02 22:26:00",
    "price": 19323.23625
  },
  {
    "date": "2022-07-02 22:31:00",
    "price": 19336.735
  },
  {
    "date": "2022-07-02 22:36:00",
    "price": 19322.9325
  },
  {
    "date": "2022-07-02 22:41:00",
    "price": 19324.2475
  },
  {
    "date": "2022-07-02 22:46:00",
    "price": 19317.0
  },
  {
    "date": "2022-07-02 22:51:00",
    "price": 19304.35
  },
  {
    "date": "2022-07-02 22:56:00",
    "price": 19303.635
  },
  {
    "date": "2022-07-02 23:01:00",
    "price": 19304.765
  },
  {
    "date": "2022-07-02 23:06:00",
    "price": 19288.54625
  },
  {
    "date": "2022-07-02 23:11:00",
    "price": 19291.03125
  }
]