[
  {
    "date": "2022-10-01 15:06:00",
    "price": 19316.466
  },
  {
    "date": "2022-10-01 15:11:00",
    "price": 19320.808
  },
  {
    "date": "2022-10-01 15:16:00",
    "price": 19331.786
  },
  {
    "date": "2022-10-01 15:21:00",
    "price": 19329.452
  },
  {
    "date": "2022-10-01 15:26:00",
    "price": 19359.09
  },
  {
    "date": "2022-10-01 15:31:00",
    "price": 19348.638
  },
  {
    "date": "2022-10-01 15:36:00",
    "price": 19336.368
  },
  {
    "date": "2022-10-01 15:41:00",
    "price": 19331.4
  },
  {
    "date": "2022-10-01 15:46:00",
    "price": 19326.23
  },
  {
    "date": "2022-10-01 15:51:00",
    "price": 19329.866
  },
  {
    "date": "2022-10-01 15:56:00",
    "price": 19335.69
  },
  {
    "date": "2022-10-01 16:01:00",
    "price": 19340.184
  },
  {
    "date": "2022-10-01 16:06:00",
    "price": 19332.282
  },
  {
    "date": "2022-10-01 16:11:00",
    "price": 19343.864
  },
  {
    "date": "2022-10-01 16:16:00",
    "price": 19295.83
  },
  {
    "date": "2022-10-01 16:21:00",
    "price": 19271.03
  },
  {
    "date": "2022-10-01 16:26:00",
    "price": 19283.862
  },
  {
    "date": "2022-10-01 16:31:00",
    "price": 19285.492
  },
  {
    "date": "2022-10-01 16:36:00",
    "price": 19293.072
  },
  {
    "date": "2022-10-01 16:41:00",
    "price": 19294.588
  },
  {
    "date": "2022-10-01 16:46:00",
    "price": 19269.48
  },
  {
    "date": "2022-10-01 16:51:00",
    "price": 19264.26
  },
  {
    "date": "2022-10-01 16:56:00",
    "price": 19279.216
  },
  {
    "date": "2022-10-01 17:01:00",
    "price": 19297.814
  },
  {
    "date": "2022-10-01 17:06:00",
    "price": 19299.314
  },
  {
    "date": "2022-10-01 17:11:00",
    "price": 19298.57
  },
  {
    "date": "2022-10-01 17:16:00",
    "price": 19291.088
  },
  {
    "date": "2022-10-01 17:21:00",
    "price": 19302.402
  },
  {
    "date": "2022-10-01 17:26:00",
    "price": 19267.538
  },
  {
    "date": "2022-10-01 17:31:00",
    "price": 19279.238
  },
  {
    "date": "2022-10-01 17:36:00",
    "price": 19282.736
  },
  {
    "date": "2022-10-01 17:41:00",
    "price": 19284.28
  },
  {
    "date": "2022-10-01 17:46:00",
    "price": 19290.072
  },
  {
    "date": "2022-10-01 17:51:00",
    "price": 19286.526
  },
  {
    "date": "2022-10-01 17:56:00",
    "price": 19278.584
  },
  {
    "date": "2022-10-01 18:01:00",
    "price": 19278.872
  },
  {
    "date": "2022-10-01 18:06:00",
    "price": 19252.592
  },
  {
    "date": "2022-10-01 18:11:00",
    "price": 19246.31
  },
  {
    "date": "2022-10-01 18:16:00",
    "price": 19252.2
  },
  {
    "date": "2022-10-01 18:21:00",
    "price": 19263.604
  },
  {
    "date": "2022-10-01 18:26:00",
    "price": 19261.958
  },
  {
    "date": "2022-10-01 18:31:00",
    "price": 19263.042
  },
  {
    "date": "2022-10-01 18:36:00",
    "price": 19254.778
  },
  {
    "date": "2022-10-01 18:41:00",
    "price": 19273.362
  },
  {
    "date": "2022-10-01 18:46:00",
    "price": 19267.188
  },
  {
    "date": "2022-10-01 18:51:00",
    "price": 19289.674
  },
  {
    "date": "2022-10-01 18:56:00",
    "price": 19296.372
  },
  {
    "date": "2022-10-01 19:01:00",
    "price": 19297.29
  },
  {
    "date": "2022-10-01 19:06:00",
    "price": 19304.638
  },
  {
    "date": "2022-10-01 19:11:00",
    "price": 19301.472
  },
  {
    "date": "2022-10-01 19:16:00",
    "price": 19309.35
  },
  {
    "date": "2022-10-01 19:21:00",
    "price": 19307.284
  },
  {
    "date": "2022-10-01 19:26:00",
    "price": 19312.84
  },
  {
    "date": "2022-10-01 19:31:00",
    "price": 19307.92
  },
  {
    "date": "2022-10-01 19:36:00",
    "price": 19297.068
  },
  {
    "date": "2022-10-01 19:41:00",
    "price": 19238.97
  },
  {
    "date": "2022-10-01 19:46:00",
    "price": 19262.912
  },
  {
    "date": "2022-10-01 19:51:00",
    "price": 19283.276
  },
  {
    "date": "2022-10-01 19:56:00",
    "price": 19282.114
  },
  {
    "date": "2022-10-01 20:01:00",
    "price": 19255.636
  },
  {
    "date": "2022-10-01 20:06:00",
    "price": 19242.326
  },
  {
    "date": "2022-10-01 20:11:00",
    "price": 19224.882
  },
  {
    "date": "2022-10-01 20:16:00",
    "price": 19227.99
  },
  {
    "date": "2022-10-01 20:21:00",
    "price": 19247.98
  },
  {
    "date": "2022-10-01 20:26:00",
    "price": 19244.454
  },
  {
    "date": "2022-10-01 20:31:00",
    "price": 19240.384
  },
  {
    "date": "2022-10-01 20:36:00",
    "price": 19248.13
  },
  {
    "date": "2022-10-01 20:41:00",
    "price": 19247.212
  },
  {
    "date": "2022-10-01 20:46:00",
    "price": 19262.442
  },
  {
    "date": "2022-10-01 20:51:00",
    "price": 19263.178
  },
  {
    "date": "2022-10-01 20:56:00",
    "price": 19254.64
  },
  {
    "date": "2022-10-01 21:01:00",
    "price": 19253.308
  },
  {
    "date": "2022-10-01 21:06:00",
    "price": 19254.578
  },
  {
    "date": "2022-10-01 21:11:00",
    "price": 19251.794
  },
  {
    "date": "2022-10-01 21:16:00",
    "price": 19260.722
  },
  {
    "date": "2022-10-01 21:21:00",
    "price": 19270.722
  },
  {
    "date": "2022-10-01 21:26:00",
    "price": 19270.962
  },
  {
    "date": "2022-10-01 21:31:00",
    "price": 19291.434
  },
  {
    "date": "2022-10-01 21:36:00",
    "price": 19298.322
  },
  {
    "date": "2022-10-01 21:41:00",
    "price": 19291.048
  },
  {
    "date": "2022-10-01 21:46:00",
    "price": 19298.756
  },
  {
    "date": "2022-10-01 21:51:00",
    "price": 19295.916
  },
  {
    "date": "2022-10-01 21:56:00",
    "price": 19297.04
  },
  {
    "date": "2022-10-01 22:01:00",
    "price": 19278.652
  },
  {
    "date": "2022-10-01 22:06:00",
    "price": 19295.788
  },
  {
    "date": "2022-10-01 22:11:00",
    "price": 19302.714
  },
  {
    "date": "2022-10-01 22:16:00",
    "price": 19294.602
  },
  {
    "date": "2022-10-01 22:21:00",
    "price": 19293.002
  },
  {
    "date": "2022-10-01 22:26:00",
    "price": 19304.434
  },
  {
    "date": "2022-10-01 22:31:00",
    "price": 19311.034
  },
  {
    "date": "2022-10-01 22:36:00",
    "price": 19317.144
  },
  {
    "date": "2022-10-01 22:41:00",
    "price": 19316.296
  },
  {
    "date": "2022-10-01 22:46:00",
    "price": 19324.146
  },
  {
    "date": "2022-10-01 22:51:00",
    "price": 19326.288
  },
  {
    "date": "2022-10-01 22:56:00",
    "price": 19328.348
  },
  {
    "date": "2022-10-01 23:01:00",
    "price": 19326.782
  },
  {
    "date": "2022-10-01 23:06:00",
    "price": 19340.34
  },
  {
    "date": "2022-10-01 23:11:00",
    "price": 19331.11
  },
  {
    "date": "2022-10-01 23:16:00",
    "price": 19314.83
  },
  {
    "date": "2022-10-01 23:21:00",
    "price": 19303.036
  },
  {
    "date": "2022-10-01 23:26:00",
    "price": 19299.796
  }
]