[
  {
    "date": "2022-07-10 06:40:00",
    "price": 1189.955
  },
  {
    "date": "2022-07-10 06:45:00",
    "price": 1189.76375
  },
  {
    "date": "2022-07-10 06:50:00",
    "price": 1189.1575
  },
  {
    "date": "2022-07-10 06:55:00",
    "price": 1188.1
  },
  {
    "date": "2022-07-10 07:00:00",
    "price": 1188.06625
  },
  {
    "date": "2022-07-10 07:05:00",
    "price": 1187.7475
  },
  {
    "date": "2022-07-10 07:10:00",
    "price": 1187.36125
  },
  {
    "date": "2022-07-10 07:15:00",
    "price": 1188.4525
  },
  {
    "date": "2022-07-10 07:20:00",
    "price": 1187.34125
  },
  {
    "date": "2022-07-10 07:25:00",
    "price": 1187.75625
  },
  {
    "date": "2022-07-10 07:30:00",
    "price": 1189.03625
  },
  {
    "date": "2022-07-10 07:35:00",
    "price": 1188.41375
  },
  {
    "date": "2022-07-10 07:40:00",
    "price": 1189.66375
  },
  {
    "date": "2022-07-10 07:45:00",
    "price": 1190.415
  },
  {
    "date": "2022-07-10 07:50:00",
    "price": 1190.00875
  },
  {
    "date": "2022-07-10 07:55:00",
    "price": 1189.86
  },
  {
    "date": "2022-07-10 08:00:00",
    "price": 1188.74125
  },
  {
    "date": "2022-07-10 08:05:00",
    "price": 1190.1975
  },
  {
    "date": "2022-07-10 08:10:00",
    "price": 1188.445
  },
  {
    "date": "2022-07-10 08:15:00",
    "price": 1188.62375
  },
  {
    "date": "2022-07-10 08:20:00",
    "price": 1188.24875
  },
  {
    "date": "2022-07-10 08:25:00",
    "price": 1189.99125
  },
  {
    "date": "2022-07-10 08:30:00",
    "price": 1190.1125
  },
  {
    "date": "2022-07-10 08:35:00",
    "price": 1190.21875
  },
  {
    "date": "2022-07-10 08:40:00",
    "price": 1187.60375
  },
  {
    "date": "2022-07-10 08:45:00",
    "price": 1187.245
  },
  {
    "date": "2022-07-10 08:50:00",
    "price": 1188.53125
  },
  {
    "date": "2022-07-10 08:55:00",
    "price": 1184.76
  },
  {
    "date": "2022-07-10 09:00:00",
    "price": 1187.4325
  },
  {
    "date": "2022-07-10 09:05:00",
    "price": 1188.35375
  },
  {
    "date": "2022-07-10 09:10:00",
    "price": 1188.43125
  },
  {
    "date": "2022-07-10 09:15:00",
    "price": 1187.77625
  },
  {
    "date": "2022-07-10 09:20:00",
    "price": 1189.4175
  },
  {
    "date": "2022-07-10 09:25:00",
    "price": 1186.195
  },
  {
    "date": "2022-07-10 09:30:00",
    "price": 1185.84625
  },
  {
    "date": "2022-07-10 09:35:00",
    "price": 1185.13625
  },
  {
    "date": "2022-07-10 09:40:00",
    "price": 1188.3125
  },
  {
    "date": "2022-07-10 09:45:00",
    "price": 1187.7575
  },
  {
    "date": "2022-07-10 09:50:00",
    "price": 1188.67375
  },
  {
    "date": "2022-07-10 09:55:00",
    "price": 1187.84125
  },
  {
    "date": "2022-07-10 10:00:00",
    "price": 1186.29875
  },
  {
    "date": "2022-07-10 10:05:00",
    "price": 1186.9575
  },
  {
    "date": "2022-07-10 10:10:00",
    "price": 1186.7575
  },
  {
    "date": "2022-07-10 10:15:00",
    "price": 1187.15125
  },
  {
    "date": "2022-07-10 10:20:00",
    "price": 1184.9725
  },
  {
    "date": "2022-07-10 10:25:00",
    "price": 1184.59125
  },
  {
    "date": "2022-07-10 10:30:00",
    "price": 1184.42
  },
  {
    "date": "2022-07-10 10:35:00",
    "price": 1184.52625
  },
  {
    "date": "2022-07-10 10:40:00",
    "price": 1186.33375
  },
  {
    "date": "2022-07-10 10:45:00",
    "price": 1184.10625
  },
  {
    "date": "2022-07-10 10:50:00",
    "price": 1180.93875
  },
  {
    "date": "2022-07-10 10:55:00",
    "price": 1180.99
  },
  {
    "date": "2022-07-10 11:00:00",
    "price": 1181.81625
  },
  {
    "date": "2022-07-10 11:05:00",
    "price": 1182.60875
  },
  {
    "date": "2022-07-10 11:10:00",
    "price": 1179.26375
  },
  {
    "date": "2022-07-10 11:15:00",
    "price": 1179.34
  },
  {
    "date": "2022-07-10 11:20:00",
    "price": 1180.28125
  },
  {
    "date": "2022-07-10 11:25:00",
    "price": 1175.14375
  },
  {
    "date": "2022-07-10 11:30:00",
    "price": 1176.87625
  },
  {
    "date": "2022-07-10 11:35:00",
    "price": 1176.525
  },
  {
    "date": "2022-07-10 11:40:00",
    "price": 1176.545
  },
  {
    "date": "2022-07-10 11:45:00",
    "price": 1179.41375
  },
  {
    "date": "2022-07-10 11:50:00",
    "price": 1183.2
  },
  {
    "date": "2022-07-10 11:55:00",
    "price": 1182.985
  },
  {
    "date": "2022-07-10 12:00:00",
    "price": 1182.5225
  },
  {
    "date": "2022-07-10 12:05:00",
    "price": 1183.16
  },
  {
    "date": "2022-07-10 12:10:00",
    "price": 1182.15875
  },
  {
    "date": "2022-07-10 12:15:00",
    "price": 1185.2575
  },
  {
    "date": "2022-07-10 12:20:00",
    "price": 1185.68375
  },
  {
    "date": "2022-07-10 12:25:00",
    "price": 1184.49125
  },
  {
    "date": "2022-07-10 12:30:00",
    "price": 1184.0625
  },
  {
    "date": "2022-07-10 12:35:00",
    "price": 1184.495
  },
  {
    "date": "2022-07-10 12:40:00",
    "price": 1183.7425
  },
  {
    "date": "2022-07-10 12:45:00",
    "price": 1182.48125
  },
  {
    "date": "2022-07-10 12:50:00",
    "price": 1181.8775
  },
  {
    "date": "2022-07-10 12:55:00",
    "price": 1182.93625
  },
  {
    "date": "2022-07-10 13:00:00",
    "price": 1183.78875
  },
  {
    "date": "2022-07-10 13:05:00",
    "price": 1181.15625
  },
  {
    "date": "2022-07-10 13:10:00",
    "price": 1180.99125
  },
  {
    "date": "2022-07-10 13:15:00",
    "price": 1179.50625
  },
  {
    "date": "2022-07-10 13:20:00",
    "price": 1177.7975
  },
  {
    "date": "2022-07-10 13:25:00",
    "price": 1177.95875
  },
  {
    "date": "2022-07-10 13:30:00",
    "price": 1177.64375
  },
  {
    "date": "2022-07-10 13:35:00",
    "price": 1174.18625
  },
  {
    "date": "2022-07-10 13:40:00",
    "price": 1173.52375
  },
  {
    "date": "2022-07-10 13:45:00",
    "price": 1173.48375
  },
  {
    "date": "2022-07-10 13:50:00",
    "price": 1173.8075
  },
  {
    "date": "2022-07-10 13:55:00",
    "price": 1173.26625
  },
  {
    "date": "2022-07-10 14:00:00",
    "price": 1175.29875
  },
  {
    "date": "2022-07-10 14:05:00",
    "price": 1171.92875
  },
  {
    "date": "2022-07-10 14:10:00",
    "price": 1169.6175
  },
  {
    "date": "2022-07-10 14:15:00",
    "price": 1168.7975
  },
  {
    "date": "2022-07-10 14:20:00",
    "price": 1171.55875
  },
  {
    "date": "2022-07-10 14:25:00",
    "price": 1168.67125
  },
  {
    "date": "2022-07-10 14:30:00",
    "price": 1163.7675
  },
  {
    "date": "2022-07-10 14:35:00",
    "price": 1161.8875
  },
  {
    "date": "2022-07-10 14:40:00",
    "price": 1158.2125
  },
  {
    "date": "2022-07-10 14:45:00",
    "price": 1158.77125
  },
  {
    "date": "2022-07-10 14:50:00",
    "price": 1159.24875
  },
  {
    "date": "2022-07-10 14:55:00",
    "price": 1158.0175
  },
  {
    "date": "2022-07-10 15:00:00",
    "price": 1158.56375
  }
]